pyspark_jira/__init__.py
pyspark_jira/jira.py
pyspark_jira-0.0.2.dist-info/LICENSE
pyspark_jira-0.0.2.dist-info/METADATA
pyspark_jira-0.0.2.dist-info/WHEEL
pyspark_jira-0.0.2.dist-info/top_level.txt
pyspark_jira-0.0.2.dist-info/RECORD
